udacity_gaussian_binomial_distributions/Binomialdistribution.py
udacity_gaussian_binomial_distributions/Gaussiandistribution.py
udacity_gaussian_binomial_distributions/Generaldistribution.py
udacity_gaussian_binomial_distributions/__init__.py
udacity_gaussian_binomial_distributions-0.1.dist-info/DESCRIPTION.rst
udacity_gaussian_binomial_distributions-0.1.dist-info/METADATA
udacity_gaussian_binomial_distributions-0.1.dist-info/RECORD
udacity_gaussian_binomial_distributions-0.1.dist-info/WHEEL
udacity_gaussian_binomial_distributions-0.1.dist-info/metadata.json
udacity_gaussian_binomial_distributions-0.1.dist-info/top_level.txt
